sxm_converter/__init__.py
sxm_converter/converter.py
sxm_converter/sxm2png.py
sxm_converter-0.2.dist-info/METADATA
sxm_converter-0.2.dist-info/WHEEL
sxm_converter-0.2.dist-info/top_level.txt
sxm_converter-0.2.dist-info/RECORD
