Metadata-Version: 2.1
Name: sxm-converter
Version: 0.2
Summary: convert .sxm(Nanonis instruments) to picture easily
Home-page: UNKNOWN
Author: CoccaGuo
Author-email: guojiadong@bnu.edu.cn
License: UNKNOWN
Platform: UNKNOWN
